TOOLS.MD
arpa2.quickder_tools-1.4.0-py3.7-nspkg.pth
arpa2/quickder_tools/__init__.py
arpa2/quickder_tools/asn1literate.py
arpa2/quickder_tools/asn2quickder.py
arpa2/quickder_tools/derdump.py
arpa2/quickder_tools/packstx.py
arpa2/quickder_tools/util.py
arpa2/quickder_tools/generators/__init__.py
arpa2/quickder_tools/generators/header.py
arpa2/quickder_tools/generators/python.py
arpa2/quickder_tools/generators/source.py
arpa2/quickder_tools/generators/testdata.py
img/derdump-screenshot.png
arpa2.quickder_tools-1.4.0.dist-info/LICENSE.MD
arpa2.quickder_tools-1.4.0.dist-info/METADATA
arpa2.quickder_tools-1.4.0.dist-info/WHEEL
arpa2.quickder_tools-1.4.0.dist-info/entry_points.txt
arpa2.quickder_tools-1.4.0.dist-info/namespace_packages.txt
arpa2.quickder_tools-1.4.0.dist-info/top_level.txt
arpa2.quickder_tools-1.4.0.dist-info/RECORD
