Metadata-Version: 2.1
Name: arpa2.quickder-tools
Version: 1.4.0
Summary: Quick DER -- Tools to work with ASN.1 specifications
Home-page: https://gitlab.com/arpa2/quick-der
Author: Rick van Rein (for the ARPA2 Quick DER project)
Author-email: rick@openfortress.nl
License: UNKNOWN
Platform: UNKNOWN
Requires-Dist: asn1ate (>=0.6.0)
Requires-Dist: colored
Requires-Dist: six
Provides-Extra: runtime
Requires-Dist: arpa2.quickder ; extra == 'runtime'
